pchemdb/__about__.py
pchemdb/__init__.py
pchemdb/crc.py
pchemdb/utils.py
pchemdb/_database/crc.json
pchemdb-0.0.2.dist-info/METADATA
pchemdb-0.0.2.dist-info/WHEEL
pchemdb-0.0.2.dist-info/licenses/LICENSE.txt
pchemdb-0.0.2.dist-info/RECORD
